clustervis/__init__.py
clustervis/colors.py
clustervis/visualization.py
clustervis-1.0.52.dist-info/licenses/LICENSE
clustervis-1.0.52.dist-info/METADATA
clustervis-1.0.52.dist-info/WHEEL
clustervis-1.0.52.dist-info/top_level.txt
clustervis-1.0.52.dist-info/RECORD
