Metadata-Version: 2.4
Name: clustervis
Version: 1.0.52
Summary: A Python package for clustering visualization
Author-email: Antonio De Angelis <deangelis.antonio122@gmail.com>
License: MIT
Requires-Python: >=3.6
License-File: LICENSE
Requires-Dist: numpy
Requires-Dist: matplotlib
Requires-Dist: scikit-learn
Dynamic: license-file
